sqlitedl
