Metadata-Version: 2.1
Name: sqlitedl
Version: 1.3.3
Summary: https://github.com/SiiHino/sqlite-database-library
Author-email: mcsiihino@mail.ru
